README.rst
setup.py
xx_wizard/__init__.py
xx_wizard/wizard.py
xx_wizard.egg-info/PKG-INFO
xx_wizard.egg-info/SOURCES.txt
xx_wizard.egg-info/dependency_links.txt
xx_wizard.egg-info/requires.txt
xx_wizard.egg-info/top_level.txt
xx_wizard.egg-info/zip-safe