Metadata-Version: 1.1
Name: xx-wizard
Version: 1.1.0
Summary: xx精灵: 键盘鼠标的监听与控制
Home-page: https://gitee.com/tianshl/key_wizard
Author: tianshl
Author-email: xiyuan91@126.com
License: MIT
Keywords: keyboard mouse pynput tkinter wizard
Platform: UNKNOWN
Classifier: License :: OSI Approved :: MIT License
Classifier: Programming Language :: Python :: 3
Classifier: Intended Audience :: Developers
Classifier: Operating System :: OS Independent
